diocli.py
diogenes8-1.0.0.dist-info/METADATA
diogenes8-1.0.0.dist-info/WHEEL
diogenes8-1.0.0.dist-info/entry_points.txt
diogenes8-1.0.0.dist-info/top_level.txt
diogenes8-1.0.0.dist-info/RECORD
